mcp_filesystem/__init__.py
mcp_filesystem/config.py
mcp_filesystem/directory_copy.py
mcp_filesystem/directory_create.py
mcp_filesystem/directory_delete.py
mcp_filesystem/directory_find.py
mcp_filesystem/directory_information.py
mcp_filesystem/directory_list.py
mcp_filesystem/directory_move.py
mcp_filesystem/directory_rename.py
mcp_filesystem/directory_tree.py
mcp_filesystem/file_copy.py
mcp_filesystem/file_create.py
mcp_filesystem/file_delete.py
mcp_filesystem/file_find.py
mcp_filesystem/file_information.py
mcp_filesystem/file_move.py
mcp_filesystem/file_read.py
mcp_filesystem/file_rename.py
mcp_filesystem/file_write.py
mcp_filesystem/path_exist.py
mcp_filesystem/system_information.py
mcp_filesystem-0.3.0.dist-info/WHEEL
mcp_filesystem-0.3.0.dist-info/entry_points.txt
mcp_filesystem-0.3.0.dist-info/METADATA
mcp_filesystem-0.3.0.dist-info/RECORD
