Metadata-Version: 2.3
Name: mcp-filesystem
Version: 0.3.0
Summary: A configurable MCP Server for Filesystem operations in Windows/Linux/MacOS, supporting stdio, streamable-http and SSE transports.
Keywords: mcp,filesystem,ai,llm,tool
Author: YANG Jiacheng
Author-email: YANG Jiacheng <yangjiacheng1996@outlook.com>
License: MIT
Classifier: Development Status :: 4 - Beta
Classifier: Intended Audience :: Developers
Classifier: License :: OSI Approved :: MIT License
Classifier: Operating System :: OS Independent
Classifier: Programming Language :: Python :: 3
Classifier: Programming Language :: Python :: 3.11
Classifier: Programming Language :: Python :: 3.12
Classifier: Programming Language :: Python :: 3.13
Classifier: Topic :: Software Development :: Libraries :: Python Modules
Requires-Dist: mcp>=1.0.0
Requires-Dist: pytest>=7.0.0 ; extra == 'dev'
Requires-Dist: pytest-cov>=4.0.0 ; extra == 'dev'
Requires-Python: >=3.11
Project-URL: Homepage, https://github.com/yangjiacheng1996/mcp_filesystem
Project-URL: Issues, https://github.com/yangjiacheng1996/mcp_filesystem/issues
Project-URL: Repository, https://github.com/yangjiacheng1996/mcp_filesystem
Provides-Extra: dev
